cornerhex-0.4.0.dist-info/METADATA
cornerhex-0.4.0.dist-info/WHEEL
cornerhex-0.4.0.dist-info/LICENSE
cornerhex/__init__.py
cornerhex/plot.py
cornerhex-0.4.0.dist-info/RECORD
