Metadata-Version: 2.1
Name: cornerhex
Version: 0.4.0
Summary: Package to visualize multi-dimensional data in hexbin pairwise plots.
Author-Email: "Sebastian.stammler" <sebastian.stammler@gmail.com>
Maintainer-Email: Sebastian Stammler <sebastian.stammler@gmail.com>
License: BSD 3-Clause License
Classifier: Development Status :: 4 - Beta
Classifier: Environment :: Console
Classifier: Intended Audience :: Developers
Classifier: Intended Audience :: Education
Classifier: Intended Audience :: Information Technology
Classifier: Intended Audience :: Science/Research
Classifier: License :: OSI Approved :: BSD License
Classifier: Natural Language :: English
Classifier: Operating System :: OS Independent
Classifier: Programming Language :: Python
Classifier: Programming Language :: Python :: 3 :: Only
Classifier: Topic :: Education
Classifier: Topic :: Scientific/Engineering
Classifier: Topic :: Scientific/Engineering :: Artificial Intelligence
Classifier: Topic :: Scientific/Engineering :: Astronomy
Classifier: Topic :: Scientific/Engineering :: Information Analysis
Classifier: Topic :: Scientific/Engineering :: Mathematics
Classifier: Topic :: Scientific/Engineering :: Physics
Classifier: Topic :: Scientific/Engineering :: Visualization
Project-URL: Homepage, https://cornerhex.readthedocs.io/
Project-URL: Repository, https://github.com/stammler/cornerhex/
Requires-Dist: matplotlib
Requires-Dist: numpy
Requires-Dist: scipy
